config_loader/__init__.py
config_loader/loader.py
config_loader/version.py
configuration_loader-0.2.0.dist-info/AUTHORS.rst
configuration_loader-0.2.0.dist-info/LICENSE
configuration_loader-0.2.0.dist-info/METADATA
configuration_loader-0.2.0.dist-info/WHEEL
configuration_loader-0.2.0.dist-info/top_level.txt
configuration_loader-0.2.0.dist-info/RECORD
